{
  "name": "network",
  "version": "3.1",
  "description": "Типовые неисправности сетевого оборудования. Расширенный по ITIL/FMEA практикам.",
  "faults": [
    {"code": "NET-LINK-001", "title": "Потеря линка на порту", "description": "Порт Down, нет трафика.", "failure_mode": "Полный отказ", "symptoms": ["link down", "port down", "interface down"], "keywords": ["link", "down", "линк", "порт"], "category": "Сетевое подключение / Связь", "recommended_actions": ["Проверить кабель", "Проверить SFP", "Counters ошибок"]},
    {"code": "NET-POE-001", "title": "Устройство не получает PoE", "description": "Камера/точка доступа не питается.", "failure_mode": "Полный отказ", "symptoms": ["poe", "не питается", "power inline"], "keywords": ["poe", "питание", "af", "at"], "category": "Питание", "recommended_actions": ["Проверить бюджет PoE", "Класс устройства", "Кабель"]},
    {"code": "NET-STP-001", "title": "Петля STP / Broadcast storm", "description": "Сеть тормозит, шторм broadcast.", "failure_mode": "Деградация", "symptoms": ["шторм", "broadcast storm", "stp loop"], "keywords": ["stp", "loop", "broadcast"], "category": "L2 / Switching", "recommended_actions": ["Найти порт с штормом", "BPDU Guard", "Storm control"]},
    {"code": "NET-SFP-001", "title": "Проблемы с SFP трансивером", "description": "Ошибки CRC, низкая мощность оптики.", "failure_mode": "Деградация", "symptoms": ["crc errors", "rx power low", "sfp"], "keywords": ["sfp", "оптика", "crc", "dom"], "category": "Сетевое подключение / Связь", "recommended_actions": ["Проверить DOM", "Поменять SFP/кабель", "Чистота коннекторов"]},
    {"code": "NET-BGP-001", "title": "BGP сосед не поднимается", "description": "Сессия в Idle/Active.", "failure_mode": "Полный отказ", "symptoms": ["bgp idle", "peer down"], "keywords": ["bgp", "peer", "as"], "category": "Маршрутизация и L3", "recommended_actions": ["Reachability", "AS/password", "ACL 179"]},
    {"code": "NET-OSPF-001", "title": "OSPF соседство ExStart/Init", "description": "Не формируется соседство.", "failure_mode": "Деградация", "symptoms": ["ospf exstart", "no neighbor"], "keywords": ["ospf", "exstart", "mtu"], "category": "Маршрутизация и L3", "recommended_actions": ["MTU", "Area/hello timers", "Auth"]},
    {"code": "NET-LAG-001", "title": "LACP не поднимается", "description": "Port-channel suspended.", "failure_mode": "Полный отказ", "symptoms": ["lacp", "port-channel down", "suspended"], "keywords": ["lacp", "bundle", "lag"], "category": "L2 / Switching", "recommended_actions": ["Mode active/passive", "Speed/duplex", "Allowed VLAN"]},
    {"code": "NET-ACL-001", "title": "ACL блокирует трафик", "description": "Легитимный трафик дропается.", "failure_mode": "Деградация", "symptoms": ["acl deny", "filtered"], "keywords": ["acl", "deny", "фильтр"], "category": "Безопасность и доступ", "recommended_actions": ["Найти ACL", "Hit counts", "Capture"]},
    {"code": "NET-MTU-001", "title": "MTU blackholing", "description": "Большие пакеты обрываются.", "failure_mode": "Деградация", "symptoms": ["mtu", "black hole", "fragment"], "keywords": ["mtu", "pmtud", "jumbo"], "category": "Маршрутизация и L3", "recommended_actions": ["Path MTU", "MSS clamp", "Test ping DF"]},
    {"code": "NET-HSRP-001", "title": "HSRP/VRRP нет активного", "description": "Нет виртуального шлюза.", "failure_mode": "Полный отказ", "symptoms": ["hsrp", "no gateway", "standby"], "keywords": ["hsrp", "vrrp", "virtual ip"], "category": "Маршрутизация и L3", "recommended_actions": ["Active/Standby", "Priority/preempt", "Track"]},
    {"code": "NET-FAN-001", "title": "Сбой вентиляторов", "description": "Fan failure, перегрев.", "failure_mode": "Деградация", "symptoms": ["fan failure", "temperature high"], "keywords": ["fan", "temperature", "thermal"], "category": "Охлаждение и вентиляция", "recommended_actions": ["Show environment", "Очистить фильтры", "Заменить fan tray"]},
    {"code": "NET-MGMT-001", "title": "Management недоступен", "description": "SSH/HTTPS не работает.", "failure_mode": "Полный отказ", "symptoms": ["ssh timeout", "management down"], "keywords": ["ssh", "management", "vty"], "category": "Мониторинг, управление и сервисы", "recommended_actions": ["Management IP", "ACL", "Console fallback"]},
    {"code": "NET-PORTSEC-001", "title": "Port Security violation err-disabled", "description": "Порт заблокирован по security.", "failure_mode": "Деградация", "symptoms": ["err-disabled", "violation"], "keywords": ["port security", "err-disable"], "category": "Безопасность и доступ", "recommended_actions": ["Причина violation", "Clear sticky", "Errdisable recovery"]},
    {"code": "NET-CPU-001", "title": "High CPU control plane", "description": "CLI медленный, соседства падают.", "failure_mode": "Деградация", "symptoms": ["high cpu", "control plane"], "keywords": ["cpu", "control plane", "high utilization"], "category": "Производительность", "recommended_actions": ["Top processes", "Storm/loop", "CoPP"]},
    {"code": "NET-QOS-001", "title": "QoS деградация голоса/видео", "description": "Jitter, потери при нагрузке.", "failure_mode": "Деградация", "symptoms": ["jitter", "voice quality bad"], "keywords": ["qos", "dscp", "jitter"], "category": "Производительность", "recommended_actions": ["Trust boundary", "Policy map", "LLQ check"]},
    {"code": "NET-NTP-001", "title": "NTP рассинхронизация", "description": "Время ушло, проблемы с certs.", "failure_mode": "Деградация", "symptoms": ["ntp unsynced", "clock skew"], "keywords": ["ntp", "time", "stratum"], "category": "Мониторинг, управление и сервисы", "recommended_actions": ["NTP servers", "Reachability", "Timezone"]},
    {"code": "NET-SNMP-001", "title": "SNMP polling timeout", "description": "NMS не получает данные.", "failure_mode": "Деградация", "symptoms": ["snmp timeout", "no response"], "keywords": ["snmp", "polling", "community"], "category": "Мониторинг, управление и сервисы", "recommended_actions": ["Community/v3 user", "ACL для NMS", "Source interface"]},
    {"code": "NET-STACK-001", "title": "Сбой стекирования", "description": "Стек распался, master lost.", "failure_mode": "Полный отказ", "symptoms": ["stack split", "member offline"], "keywords": ["stack", "stackwise", "vsf"], "category": "Аппаратная часть", "recommended_actions": ["Stack cables", "Master/priority", "Firmware match"]},
    {"code": "NET-PSU-001", "title": "Отказ PSU коммутатора", "description": "Работа на одном блоке.", "failure_mode": "Деградация", "symptoms": ["psu failed", "redundant power lost"], "keywords": ["psu", "power supply"], "category": "Питание", "recommended_actions": ["Status PSU", "Переподключить", "Заменить"]},
    {"code": "NET-VLAN-001", "title": "Меж-VLAN routing не работает", "description": "Трафик между VLAN не проходит.", "failure_mode": "Деградация", "symptoms": ["no inter vlan", "svi down"], "keywords": ["vlan", "svi", "routing"], "category": "L2/L3", "recommended_actions": ["Access/trunk", "SVI status", "ACL"]},
    {"code": "NET-DHCP-001", "title": "DHCP relay не работает", "description": "Клиенты не получают IP.", "failure_mode": "Полный отказ", "symptoms": ["dhcp timeout", "169.254"], "keywords": ["dhcp", "relay", "ip helper"], "category": "L3", "recommended_actions": ["ip helper-address", "Server reachability", "Snooping trusted"]},
    {"code": "NET-IGMP-001", "title": "Multicast не доходит", "description": "IPTV/multicast не работает.", "failure_mode": "Деградация", "symptoms": ["no multicast", "igmp join fail"], "keywords": ["multicast", "igmp", "pim"], "category": "L2/L3", "recommended_actions": ["IGMP snooping mrouter", "PIM config", "RP"]},
    {"code": "NET-FLAP-001", "title": "Flapping порта", "description": "Порт up/down циклически.", "failure_mode": "Интермиттент", "symptoms": ["flapping", "up down"], "keywords": ["flap", "link state"], "category": "Сетевое подключение / Связь", "recommended_actions": ["Кабель/SFP", "Debounce", "Auto-neg"]},
    {"code": "NET-AAA-001", "title": "AAA/RADIUS не пускает", "description": "Login timeout или reject.", "failure_mode": "Полный отказ", "symptoms": ["aaa timeout", "radius fail"], "keywords": ["aaa", "radius", "tacacs"], "category": "Безопасность и доступ", "recommended_actions": ["Server reachability", "Shared secret", "Fallback local"]},
    {"code": "NET-ARP-001", "title": "ARP issues / incomplete", "description": "ARP не резолвит, incomplete entries.", "failure_mode": "Деградация", "symptoms": ["arp incomplete", "no mac"], "keywords": ["arp", "incomplete"], "category": "L3", "recommended_actions": ["Proxy arp", "ACL", "Gratuitous"]},
    {"code": "NET-SPAN-001", "title": "SPAN/RSPAN не работает", "description": "Мониторинг порт не получает трафик.", "failure_mode": "Деградация", "symptoms": ["span no traffic", "monitor session"], "keywords": ["span", "monitor", "rspan"], "category": "Мониторинг, управление и сервисы", "recommended_actions": ["Source/dest ports", "Vlan filter", "Direction rx/tx"]},
    {"code": "NET-ECN-001", "title": "ECN / congestion notification", "description": "Проблемы с marked packets, drops.", "failure_mode": "Деградация", "symptoms": ["ecn", "congestion"], "keywords": ["ecn", "wred"], "category": "Производительность", "recommended_actions": ["WRED config", "Queue thresholds", "Test with iperf"]},
    {"code": "NET-FIREWALL-001", "title": "Zone-based firewall blocks", "description": "Трафик дропается zone policy.", "failure_mode": "Деградация", "symptoms": ["zone drop", "policy deny"], "keywords": ["zone", "fw", "policy"], "category": "Безопасность и доступ", "recommended_actions": ["Show policy", "Class-map", "Log drops"]},
    {"code": "NET-VXLAN-001", "title": "VXLAN / EVPN issues", "description": "VTEP не видит remote.", "failure_mode": "Полный отказ", "symptoms": ["vxlan vni down", "no evpn"], "keywords": ["vxlan", "evpn", "vtep"], "category": "L2/L3", "recommended_actions": ["VNI state", "Underlay", "BGP EVPN"]},
    {"code": "NET-LOAD-001", "title": "Load balancer pool down", "description": "Backend servers marked down.", "failure_mode": "Деградация", "symptoms": ["pool down", "health check fail"], "keywords": ["loadbalancer", "pool", "health"], "category": "Производительность", "recommended_actions": ["Health check config", "Backend status", "Logs"]},
    {"code": "NET-WIRELESS-001", "title": "AP не присоединяется к WLC", "description": "Access point не регистрируется.", "failure_mode": "Полный отказ", "symptoms": ["ap not join", "wlc"], "keywords": ["ap", "wlc", "capwap"], "category": "Сетевое подключение / Связь", "recommended_actions": ["CAPWAP reachability", "Certificates", "WLC config"]},
    {"code": "NET-CABLE-001", "title": "Проблемы с кабельным хозяйством", "description": "Кросс, патч-панель, dirty fiber.", "failure_mode": "Деградация", "symptoms": ["dirty fiber", "bad patch"], "keywords": ["кабель", "patch", "fiber", "dirty"], "category": "Сетевое подключение / Связь", "recommended_actions": ["Inspect patch", "Clean fiber", "OTDR if needed"]},
    {"code": "NET-SDWAN-001", "title": "SD-WAN tunnel down", "description": "Overlay не поднимается.", "failure_mode": "Полный отказ", "symptoms": ["sdwan tunnel down", "omp down"], "keywords": ["sdwan", "tunnel", "omp"], "category": "Маршрутизация и L3", "recommended_actions": ["Underlay", "Cert", "OMP status"]},
    {"code": "NET-MACSEC-001", "title": "MACsec session not up", "description": "Шифрование линка не работает.", "failure_mode": "Деградация", "symptoms": ["macsec fail", "mka"], "keywords": ["macsec", "mka", "encryption"], "category": "Безопасность и доступ", "recommended_actions": ["MKA policy", "Pre-shared key", "Show macsec"]},
    {"code": "NET-OTDR-001", "title": "Fiber cut / high loss", "description": "Высокие потери на волокне.", "failure_mode": "Полный отказ", "symptoms": ["high loss", "fiber cut"], "keywords": ["fiber", "loss", "otdr"], "category": "Сетевое подключение / Связь", "recommended_actions": ["OTDR test", "Repair splice", "Replace fiber"]},
    {"code": "NET-AUTONEG-001", "title": "Auto-negotiation mismatch", "description": "Link up но ошибки, duplex mismatch.", "failure_mode": "Деградация", "symptoms": ["duplex mismatch", "late collision"], "keywords": ["autoneg", "duplex", "speed"], "category": "Сетевое подключение / Связь", "recommended_actions": ["Hardcode speed/duplex", "Check both ends", "Cables"]},
    {"code": "NET-ISIS-001", "title": "ISIS adjacency not forming", "description": "ISIS не поднимает adjacency.", "failure_mode": "Полный отказ", "symptoms": ["isis adj down", "no isis"], "keywords": ["isis", "adjacency", "clns"], "category": "Маршрутизация и L3", "recommended_actions": ["MTU", "NET address", "Auth", "Level"]},
    {"code": "NET-MPLS-001", "title": "MPLS LDP session down", "description": "LDP не поднимается.", "failure_mode": "Полный отказ", "symptoms": ["ldp session down"], "keywords": ["mpls", "ldp", "label"], "category": "Маршрутизация и L3", "recommended_actions": ["IGP", "Router ID", "Transport address"]},
    {"code": "NET-BFD-001", "title": "BFD session down", "description": "BFD не обнаруживает быстро.", "failure_mode": "Деградация", "symptoms": ["bfd down", "fast detect"], "keywords": ["bfd", "fast detect"], "category": "Маршрутизация и L3", "recommended_actions": ["BFD config", "Timers match", "ACL"]},
    {"code": "NET-TELEMETRY-001", "title": "Streaming telemetry not sending", "description": "No data to collector.", "failure_mode": "Деградация", "symptoms": ["no telemetry", "grpc fail"], "keywords": ["telemetry", "grpc", "yang"], "category": "Мониторинг, управление и сервисы", "recommended_actions": ["Destination", "Subscription", "Cert"]},
    {"code": "NET-DOT1X-001", "title": "802.1X authentication fail", "description": "Port not authorized.", "failure_mode": "Полный отказ", "symptoms": ["dot1x fail", "unauthorized"], "keywords": ["dot1x", "radius", "mab"], "category": "Безопасность и доступ", "recommended_actions": ["Radius", "Supplicant", "MAB fallback"]},
    {"code": "NET-ROUTEMAP-001", "title": "Route-map not matching", "description": "Prefix not filtered as expected.", "failure_mode": "Деградация", "symptoms": ["route map issue"], "keywords": ["route-map", "prefix-list"], "category": "Маршрутизация и L3", "recommended_actions": ["Show route-map", "ACL/prefix", "Sequence"]},
    {"code": "NET-OSPFV3-001", "title": "OSPFv3 issues IPv6", "description": "IPv6 routing not working.", "failure_mode": "Полный отказ", "symptoms": ["ospfv3 down"], "keywords": ["ospfv3", "ipv6"], "category": "Маршрутизация и L3", "recommended_actions": ["Address family", "Area", "Auth"]},
    {"code": "NET-VRF-001", "title": "VRF leak or isolation issue", "description": "Traffic leaking between VRF.", "failure_mode": "Деградация", "symptoms": ["vrf leak"], "keywords": ["vrf", "import", "export"], "category": "L3", "recommended_actions": ["RT import/export", "Route leaking config", "Test ping"]},
    {"code": "NET-PIM-001", "title": "PIM sparse mode problems", "description": "Multicast RP issues.", "failure_mode": "Деградация", "symptoms": ["pim rp", "no (*,G)"], "keywords": ["pim", "rp", "sparse"], "category": "L2/L3", "recommended_actions": ["RP config", "BSR", "Join"]},
    {"code": "NET-OTV-001", "title": "OTV adjacency down", "description": "Site not extending.", "failure_mode": "Полный отказ", "symptoms": ["otv adj down"], "keywords": ["otv", "overlay"], "category": "L2/L3", "recommended_actions": ["Site VLAN", "Join interface", "ED"]},
    {"code": "NET-FCOE-001", "title": "FCoE not logging in", "description": "FC over Ethernet issues.", "failure_mode": "Полный отказ", "symptoms": ["fcoe login fail"], "keywords": ["fcoe", "vfc", "fc"], "category": "Хранение данных", "recommended_actions": ["VFC", "VSAN", "FIP"]},
    {"code": "NET-STORAGE-001", "title": "iSCSI login fail", "description": "Initiator not connecting to target.", "failure_mode": "Полный отказ", "symptoms": ["iscsi login error"], "keywords": ["iscsi", "target", "initiator"], "category": "Хранение данных", "recommended_actions": ["Target IP", "CHAP", "Portal", "Firewall 3260"]},
    {"code": "NET-CABLE-002", "title": "Dirty or damaged fiber", "description": "High BER, power low.", "failure_mode": "Деградация", "symptoms": ["high ber", "dirty fiber"], "keywords": ["fiber", "dirty", "ber", "power"], "category": "Сетевое подключение / Связь", "recommended_actions": ["Clean connectors", "Inspect", "Replace patch cord"]}
  ]
}